<?xml version="1.0" ?>
<root t='150' id='1' V150='12' creationTimestamp='0x11d4271fc32' V1='4' name='119' incarnation='5'>
  <rootElem t='167' id='2' V167='16' occurMaxTimes='1' minSize='1' maxSize='6' dataType='2' ediElemType='5' ediElemRef='119' repHandlerStruct='' visible='true' nullable='true' inheritsFrom='' autoAddNew='true' V281='3' V1='4' name='E119'>
    <structNode t='150' idref='1'/>
    <purpose>The (mileage) factor published for rating purposes in the appropriate tariff</purpose>
  </rootElem>
  <child t='162' id='3' V1='4' name='Representations' incarnation='1'>
  </child>
  <child t='165' id='4' V1='4' name='Document Bindings' incarnation='1'>
  </child>
</root>
