<?xml version="1.0" ?>
<root t='150' id='1' V150='12' creationTimestamp='0x11d4271fa7e' V1='4' name='66' incarnation='6'>
  <rootElem t='167' id='2' V167='16' occurMaxTimes='1' minSize='1' maxSize='2' dataType='2' ediElemType='5' ediElemRef='66' repHandlerStruct='' visible='true' nullable='true' inheritsFrom='' inheritsFromCopyRule='16' needInheritInit='true' V281='3' V1='4' name='E66'>
    <structNode t='150' idref='1'/>
    <purpose>Code designating the system/method of code structure used for Identification Code (67)</purpose>
    <child t='167' id='3' V167='16' occurMaxTimes='1' minSize='-1' maxSize='-1' dataType='2' elemType='5' repHandlerStruct='' visible='true' inheritsFrom='' autoAddNew='true' V281='3' V1='4' name='1' description='D-U-N-S Number, Dun &amp; Bradstreet' incarnation='1'>
      <structNode t='150' idref='1'/>
    </child>
    <child t='167' id='4' V167='16' occurMaxTimes='1' minSize='-1' maxSize='-1' dataType='2' elemType='5' repHandlerStruct='' visible='true' inheritsFrom='' autoAddNew='true' V281='3' V1='4' name='2' description='Standard Carrier Alpha Code (SCAC)' incarnation='1'>
      <structNode t='150' idref='1'/>
    </child>
    <child t='167' id='5' V167='16' occurMaxTimes='1' minSize='-1' maxSize='-1' dataType='2' elemType='5' repHandlerStruct='' visible='true' inheritsFrom='' autoAddNew='true' V281='3' V1='4' name='3' description='Federal Maritime Commission (Ocean) (FMC)' incarnation='1'>
      <structNode t='150' idref='1'/>
    </child>
    <child t='167' id='6' V167='16' occurMaxTimes='1' minSize='-1' maxSize='-1' dataType='2' elemType='5' repHandlerStruct='' visible='true' inheritsFrom='' autoAddNew='true' V281='3' V1='4' name='4' description='International Air Transport Association (IATA)' incarnation='1'>
      <structNode t='150' idref='1'/>
    </child>
    <child t='167' id='7' V167='16' occurMaxTimes='1' minSize='-1' maxSize='-1' dataType='2' elemType='5' repHandlerStruct='' visible='true' inheritsFrom='' autoAddNew='true' V281='3' V1='4' name='6' description='Plant Code' incarnation='1'>
      <structNode t='150' idref='1'/>
    </child>
    <child t='167' id='8' V167='16' occurMaxTimes='1' minSize='-1' maxSize='-1' dataType='2' elemType='5' repHandlerStruct='' visible='true' inheritsFrom='' autoAddNew='true' V281='3' V1='4' name='7' description='Loading Dock' incarnation='1'>
      <structNode t='150' idref='1'/>
    </child>
    <child t='167' id='9' V167='16' occurMaxTimes='1' minSize='-1' maxSize='-1' dataType='2' elemType='5' repHandlerStruct='' visible='true' inheritsFrom='' autoAddNew='true' V281='3' V1='4' name='8' description='UCC/EAN Global Product Identification Prefix' incarnation='1'>
      <structNode t='150' idref='1'/>
    </child>
    <child t='167' id='10' V167='16' occurMaxTimes='1' minSize='-1' maxSize='-1' dataType='2' elemType='5' repHandlerStruct='' visible='true' inheritsFrom='' autoAddNew='true' V281='3' V1='4' name='9' description='D-U-N-S+4, D-U-N-S Number with Four Character Suffix' incarnation='1'>
      <structNode t='150' idref='1'/>
    </child>
    <child t='167' id='11' V167='16' occurMaxTimes='1' minSize='-1' maxSize='-1' dataType='2' elemType='5' repHandlerStruct='' visible='true' inheritsFrom='' autoAddNew='true' V281='3' V1='4' name='A' description='U.S. Customs Carrier Identification' incarnation='1'>
      <structNode t='150' idref='1'/>
    </child>
    <child t='167' id='12' V167='16' occurMaxTimes='1' minSize='-1' maxSize='-1' dataType='2' elemType='5' repHandlerStruct='' visible='true' inheritsFrom='' autoAddNew='true' V281='3' V1='4' name='C' description='Insured&apos;s Changed Unique Identification Number' incarnation='1'>
      <structNode t='150' idref='1'/>
    </child>
    <child t='167' id='13' V167='16' occurMaxTimes='1' minSize='-1' maxSize='-1' dataType='2' elemType='5' repHandlerStruct='' visible='true' inheritsFrom='' autoAddNew='true' V281='3' V1='4' name='D' description='Census Schedule D' incarnation='1'>
      <structNode t='150' idref='1'/>
    </child>
    <child t='167' id='14' V167='16' occurMaxTimes='1' minSize='-1' maxSize='-1' dataType='2' elemType='5' repHandlerStruct='' visible='true' inheritsFrom='' autoAddNew='true' V281='3' V1='4' name='E' description='Hazard Insurance Policy Number' incarnation='1'>
      <structNode t='150' idref='1'/>
    </child>
    <child t='167' id='15' V167='16' occurMaxTimes='1' minSize='-1' maxSize='-1' dataType='2' elemType='5' repHandlerStruct='' visible='true' inheritsFrom='' autoAddNew='true' V281='3' V1='4' name='F' description='Document Custodian Identification Number' incarnation='1'>
      <structNode t='150' idref='1'/>
    </child>
    <child t='167' id='16' V167='16' occurMaxTimes='1' minSize='-1' maxSize='-1' dataType='2' elemType='5' repHandlerStruct='' visible='true' inheritsFrom='' autoAddNew='true' V281='3' V1='4' name='G' description='Payee Identification Number' incarnation='1'>
      <structNode t='150' idref='1'/>
    </child>
    <child t='167' id='17' V167='16' occurMaxTimes='1' minSize='-1' maxSize='-1' dataType='2' elemType='5' repHandlerStruct='' visible='true' inheritsFrom='' autoAddNew='true' V281='3' V1='4' name='I' description='Secondary Marketing Investor Assigned Number' incarnation='1'>
      <structNode t='150' idref='1'/>
    </child>
    <child t='167' id='18' V167='16' occurMaxTimes='1' minSize='-1' maxSize='-1' dataType='2' elemType='5' repHandlerStruct='' visible='true' inheritsFrom='' autoAddNew='true' V281='3' V1='4' name='J' description='Mortgage Electronic Registration System Organization Identifier' incarnation='1'>
      <structNode t='150' idref='1'/>
    </child>
    <child t='167' id='19' V167='16' occurMaxTimes='1' minSize='-1' maxSize='-1' dataType='2' elemType='5' repHandlerStruct='' visible='true' inheritsFrom='' autoAddNew='true' V281='3' V1='4' name='K' description='Census Schedule K' incarnation='1'>
      <structNode t='150' idref='1'/>
    </child>
    <child t='167' id='20' V167='16' occurMaxTimes='1' minSize='-1' maxSize='-1' dataType='2' elemType='5' repHandlerStruct='' visible='true' inheritsFrom='' autoAddNew='true' V281='3' V1='4' name='L' description='Investor Assigned Identification Number' incarnation='1'>
      <structNode t='150' idref='1'/>
    </child>
    <child t='167' id='21' V167='16' occurMaxTimes='1' minSize='-1' maxSize='-1' dataType='2' elemType='5' repHandlerStruct='' visible='true' inheritsFrom='' autoAddNew='true' V281='3' V1='4' name='N' description='Insured&apos;s Unique Identification Number' incarnation='1'>
      <structNode t='150' idref='1'/>
    </child>
    <child t='167' id='22' V167='16' occurMaxTimes='1' minSize='-1' maxSize='-1' dataType='2' elemType='5' repHandlerStruct='' visible='true' inheritsFrom='' autoAddNew='true' V281='3' V1='4' name='S' description='Title Insurance Policy Number' incarnation='1'>
      <structNode t='150' idref='1'/>
    </child>
    <child t='167' id='23' V167='16' occurMaxTimes='1' minSize='-1' maxSize='-1' dataType='2' elemType='5' repHandlerStruct='' visible='true' inheritsFrom='' autoAddNew='true' V281='3' V1='4' name='10' description='Department of Defense Activity Address Code (DODAAC)' incarnation='1'>
      <structNode t='150' idref='1'/>
    </child>
    <child t='167' id='24' V167='16' occurMaxTimes='1' minSize='-1' maxSize='-1' dataType='2' elemType='5' repHandlerStruct='' visible='true' inheritsFrom='' autoAddNew='true' V281='3' V1='4' name='11' description='Drug Enforcement Administration (DEA)' incarnation='1'>
      <structNode t='150' idref='1'/>
    </child>
    <child t='167' id='25' V167='16' occurMaxTimes='1' minSize='-1' maxSize='-1' dataType='2' elemType='5' repHandlerStruct='' visible='true' inheritsFrom='' autoAddNew='true' V281='3' V1='4' name='12' description='Telephone Number (Phone)' incarnation='1'>
      <structNode t='150' idref='1'/>
    </child>
    <child t='167' id='26' V167='16' occurMaxTimes='1' minSize='-1' maxSize='-1' dataType='2' elemType='5' repHandlerStruct='' visible='true' inheritsFrom='' autoAddNew='true' V281='3' V1='4' name='13' description='Federal Reserve Routing Code (FRRC)' incarnation='1'>
      <structNode t='150' idref='1'/>
    </child>
    <child t='167' id='27' V167='16' occurMaxTimes='1' minSize='-1' maxSize='-1' dataType='2' elemType='5' repHandlerStruct='' visible='true' inheritsFrom='' autoAddNew='true' V281='3' V1='4' name='14' description='UCC/EAN Location Code Prefix' incarnation='1'>
      <structNode t='150' idref='1'/>
    </child>
    <child t='167' id='28' V167='16' occurMaxTimes='1' minSize='-1' maxSize='-1' dataType='2' elemType='5' repHandlerStruct='' visible='true' inheritsFrom='' autoAddNew='true' V281='3' V1='4' name='15' description='Standard Address Number (SAN)' incarnation='1'>
      <structNode t='150' idref='1'/>
    </child>
    <child t='167' id='29' V167='16' occurMaxTimes='1' minSize='-1' maxSize='-1' dataType='2' elemType='5' repHandlerStruct='' visible='true' inheritsFrom='' autoAddNew='true' V281='3' V1='4' name='16' description='ZIP Code' incarnation='1'>
      <structNode t='150' idref='1'/>
    </child>
    <child t='167' id='30' V167='16' occurMaxTimes='1' minSize='-1' maxSize='-1' dataType='2' elemType='5' repHandlerStruct='' visible='true' inheritsFrom='' autoAddNew='true' V281='3' V1='4' name='17' description='Automated Broker Interface (ABI) Routing Code' incarnation='1'>
      <structNode t='150' idref='1'/>
    </child>
    <child t='167' id='31' V167='16' occurMaxTimes='1' minSize='-1' maxSize='-1' dataType='2' elemType='5' repHandlerStruct='' visible='true' inheritsFrom='' autoAddNew='true' V281='3' V1='4' name='19' description='FIPS-55 (Named Populated Places)' incarnation='1'>
      <structNode t='150' idref='1'/>
    </child>
    <child t='167' id='32' V167='16' occurMaxTimes='1' minSize='-1' maxSize='-1' dataType='2' elemType='5' repHandlerStruct='' visible='true' inheritsFrom='' autoAddNew='true' V281='3' V1='4' name='20' description='Standard Point Location Code (SPLC)' incarnation='1'>
      <structNode t='150' idref='1'/>
    </child>
    <child t='167' id='33' V167='16' occurMaxTimes='1' minSize='-1' maxSize='-1' dataType='2' elemType='5' repHandlerStruct='' visible='true' inheritsFrom='' autoAddNew='true' V281='3' V1='4' name='21' description='Health Industry Number (HIN)' incarnation='1'>
      <structNode t='150' idref='1'/>
    </child>
    <child t='167' id='34' V167='16' occurMaxTimes='1' minSize='-1' maxSize='-1' dataType='2' elemType='5' repHandlerStruct='' visible='true' inheritsFrom='' autoAddNew='true' V281='3' V1='4' name='22' description='Council of Petroleum Accounting Societies code (COPAS)' incarnation='1'>
      <structNode t='150' idref='1'/>
    </child>
    <child t='167' id='35' V167='16' occurMaxTimes='1' minSize='-1' maxSize='-1' dataType='2' elemType='5' repHandlerStruct='' visible='true' inheritsFrom='' autoAddNew='true' V281='3' V1='4' name='23' description='Journal of Commerce (JOC)' incarnation='1'>
      <structNode t='150' idref='1'/>
    </child>
    <child t='167' id='36' V167='16' occurMaxTimes='1' minSize='-1' maxSize='-1' dataType='2' elemType='5' repHandlerStruct='' visible='true' inheritsFrom='' autoAddNew='true' V281='3' V1='4' name='24' description='Employer&apos;s Identification Number' incarnation='1'>
      <structNode t='150' idref='1'/>
    </child>
    <child t='167' id='37' V167='16' occurMaxTimes='1' minSize='-1' maxSize='-1' dataType='2' elemType='5' repHandlerStruct='' visible='true' inheritsFrom='' autoAddNew='true' V281='3' V1='4' name='25' description='Carrier&apos;s Customer Code' incarnation='1'>
      <structNode t='150' idref='1'/>
    </child>
    <child t='167' id='38' V167='16' occurMaxTimes='1' minSize='-1' maxSize='-1' dataType='2' elemType='5' repHandlerStruct='' visible='true' inheritsFrom='' autoAddNew='true' V281='3' V1='4' name='26' description='Petroleum Accountants Society of Canada Company Code' incarnation='1'>
      <structNode t='150' idref='1'/>
    </child>
    <child t='167' id='39' V167='16' occurMaxTimes='1' minSize='-1' maxSize='-1' dataType='2' elemType='5' repHandlerStruct='' visible='true' inheritsFrom='' autoAddNew='true' V281='3' V1='4' name='27' description='Government Bill Of Lading Office Code (GBLOC)' incarnation='1'>
      <structNode t='150' idref='1'/>
    </child>
    <child t='167' id='40' V167='16' occurMaxTimes='1' minSize='-1' maxSize='-1' dataType='2' elemType='5' repHandlerStruct='' visible='true' inheritsFrom='' autoAddNew='true' V281='3' V1='4' name='28' description='American Paper Institute' incarnation='1'>
      <structNode t='150' idref='1'/>
    </child>
    <child t='167' id='41' V167='16' occurMaxTimes='1' minSize='-1' maxSize='-1' dataType='2' elemType='5' repHandlerStruct='' visible='true' inheritsFrom='' autoAddNew='true' V281='3' V1='4' name='29' description='Grid Location and Facility Code' incarnation='1'>
      <structNode t='150' idref='1'/>
    </child>
    <child t='167' id='42' V167='16' occurMaxTimes='1' minSize='-1' maxSize='-1' dataType='2' elemType='5' repHandlerStruct='' visible='true' inheritsFrom='' autoAddNew='true' V281='3' V1='4' name='30' description='American Petroleum Institute Location Code' incarnation='1'>
      <structNode t='150' idref='1'/>
    </child>
    <child t='167' id='43' V167='16' occurMaxTimes='1' minSize='-1' maxSize='-1' dataType='2' elemType='5' repHandlerStruct='' visible='true' inheritsFrom='' autoAddNew='true' V281='3' V1='4' name='31' description='Bank Identification Code' incarnation='1'>
      <structNode t='150' idref='1'/>
    </child>
    <child t='167' id='44' V167='16' occurMaxTimes='1' minSize='-1' maxSize='-1' dataType='2' elemType='5' repHandlerStruct='' visible='true' inheritsFrom='' autoAddNew='true' V281='3' V1='4' name='32' description='Assigned by Property Operator' incarnation='1'>
      <structNode t='150' idref='1'/>
    </child>
    <child t='167' id='45' V167='16' occurMaxTimes='1' minSize='-1' maxSize='-1' dataType='2' elemType='5' repHandlerStruct='' visible='true' inheritsFrom='' autoAddNew='true' V281='3' V1='4' name='33' description='Commercial and Government Entity (CAGE)' incarnation='1'>
      <structNode t='150' idref='1'/>
    </child>
    <child t='167' id='46' V167='16' occurMaxTimes='1' minSize='-1' maxSize='-1' dataType='2' elemType='5' repHandlerStruct='' visible='true' inheritsFrom='' autoAddNew='true' V281='3' V1='4' name='34' description='Social Security Number' incarnation='1'>
      <structNode t='150' idref='1'/>
    </child>
    <child t='167' id='47' V167='16' occurMaxTimes='1' minSize='-1' maxSize='-1' dataType='2' elemType='5' repHandlerStruct='' visible='true' inheritsFrom='' autoAddNew='true' V281='3' V1='4' name='35' description='Electronic Mail Internal System Address Code' incarnation='1'>
      <structNode t='150' idref='1'/>
    </child>
    <child t='167' id='48' V167='16' occurMaxTimes='1' minSize='-1' maxSize='-1' dataType='2' elemType='5' repHandlerStruct='' visible='true' inheritsFrom='' autoAddNew='true' V281='3' V1='4' name='36' description='Customs House Broker License Number' incarnation='1'>
      <structNode t='150' idref='1'/>
    </child>
    <child t='167' id='49' V167='16' occurMaxTimes='1' minSize='-1' maxSize='-1' dataType='2' elemType='5' repHandlerStruct='' visible='true' inheritsFrom='' autoAddNew='true' V281='3' V1='4' name='37' description='United Nations Vendor Code' incarnation='1'>
      <structNode t='150' idref='1'/>
    </child>
    <child t='167' id='50' V167='16' occurMaxTimes='1' minSize='-1' maxSize='-1' dataType='2' elemType='5' repHandlerStruct='' visible='true' inheritsFrom='' autoAddNew='true' V281='3' V1='4' name='38' description='Country Code' incarnation='1'>
      <structNode t='150' idref='1'/>
    </child>
    <child t='167' id='51' V167='16' occurMaxTimes='1' minSize='-1' maxSize='-1' dataType='2' elemType='5' repHandlerStruct='' visible='true' inheritsFrom='' autoAddNew='true' V281='3' V1='4' name='39' description='Local Union Number' incarnation='1'>
      <structNode t='150' idref='1'/>
    </child>
    <child t='167' id='52' V167='16' occurMaxTimes='1' minSize='-1' maxSize='-1' dataType='2' elemType='5' repHandlerStruct='' visible='true' inheritsFrom='' autoAddNew='true' V281='3' V1='4' name='40' description='Electronic Mail User Code' incarnation='1'>
      <structNode t='150' idref='1'/>
    </child>
    <child t='167' id='53' V167='16' occurMaxTimes='1' minSize='-1' maxSize='-1' dataType='2' elemType='5' repHandlerStruct='' visible='true' inheritsFrom='' autoAddNew='true' V281='3' V1='4' name='41' description='Telecommunications Carrier Identification Code' incarnation='1'>
      <structNode t='150' idref='1'/>
    </child>
    <child t='167' id='54' V167='16' occurMaxTimes='1' minSize='-1' maxSize='-1' dataType='2' elemType='5' repHandlerStruct='' visible='true' inheritsFrom='' autoAddNew='true' V281='3' V1='4' name='42' description='Telecommunications Pseudo Carrier Identification Code' incarnation='1'>
      <structNode t='150' idref='1'/>
    </child>
    <child t='167' id='55' V167='16' occurMaxTimes='1' minSize='-1' maxSize='-1' dataType='2' elemType='5' repHandlerStruct='' visible='true' inheritsFrom='' autoAddNew='true' V281='3' V1='4' name='43' description='Alternate Social Security Number' incarnation='1'>
      <structNode t='150' idref='1'/>
    </child>
    <child t='167' id='56' V167='16' occurMaxTimes='1' minSize='-1' maxSize='-1' dataType='2' elemType='5' repHandlerStruct='' visible='true' inheritsFrom='' autoAddNew='true' V281='3' V1='4' name='44' description='Return Sequence Number' incarnation='1'>
      <structNode t='150' idref='1'/>
    </child>
    <child t='167' id='57' V167='16' occurMaxTimes='1' minSize='-1' maxSize='-1' dataType='2' elemType='5' repHandlerStruct='' visible='true' inheritsFrom='' autoAddNew='true' V281='3' V1='4' name='45' description='Declaration Control Number' incarnation='1'>
      <structNode t='150' idref='1'/>
    </child>
    <child t='167' id='58' V167='16' occurMaxTimes='1' minSize='-1' maxSize='-1' dataType='2' elemType='5' repHandlerStruct='' visible='true' inheritsFrom='' autoAddNew='true' V281='3' V1='4' name='46' description='Electronic Transmitter Identification Number (ETIN)' incarnation='1'>
      <structNode t='150' idref='1'/>
    </child>
    <child t='167' id='59' V167='16' occurMaxTimes='1' minSize='-1' maxSize='-1' dataType='2' elemType='5' repHandlerStruct='' visible='true' inheritsFrom='' autoAddNew='true' V281='3' V1='4' name='47' description='Tax Authority Identification' incarnation='1'>
      <structNode t='150' idref='1'/>
    </child>
    <child t='167' id='60' V167='16' occurMaxTimes='1' minSize='-1' maxSize='-1' dataType='2' elemType='5' repHandlerStruct='' visible='true' inheritsFrom='' autoAddNew='true' V281='3' V1='4' name='48' description='Electronic Filer Identification Number (EFIN)' incarnation='1'>
      <structNode t='150' idref='1'/>
    </child>
    <child t='167' id='61' V167='16' occurMaxTimes='1' minSize='-1' maxSize='-1' dataType='2' elemType='5' repHandlerStruct='' visible='true' inheritsFrom='' autoAddNew='true' V281='3' V1='4' name='49' description='State Identification Number' incarnation='1'>
      <structNode t='150' idref='1'/>
    </child>
    <child t='167' id='62' V167='16' occurMaxTimes='1' minSize='-1' maxSize='-1' dataType='2' elemType='5' repHandlerStruct='' visible='true' inheritsFrom='' autoAddNew='true' V281='3' V1='4' name='50' description='Business License Number' incarnation='1'>
      <structNode t='150' idref='1'/>
    </child>
    <child t='167' id='63' V167='16' occurMaxTimes='1' minSize='-1' maxSize='-1' dataType='2' elemType='5' repHandlerStruct='' visible='true' inheritsFrom='' autoAddNew='true' V281='3' V1='4' name='51' description='Fuel Inventory Adjustment Identification' incarnation='1'>
      <structNode t='150' idref='1'/>
    </child>
    <child t='167' id='64' V167='16' occurMaxTimes='1' minSize='-1' maxSize='-1' dataType='2' elemType='5' repHandlerStruct='' visible='true' inheritsFrom='' autoAddNew='true' V281='3' V1='4' name='53' description='Building' incarnation='1'>
      <structNode t='150' idref='1'/>
    </child>
    <child t='167' id='65' V167='16' occurMaxTimes='1' minSize='-1' maxSize='-1' dataType='2' elemType='5' repHandlerStruct='' visible='true' inheritsFrom='' autoAddNew='true' V281='3' V1='4' name='54' description='Warehouse' incarnation='1'>
      <structNode t='150' idref='1'/>
    </child>
    <child t='167' id='66' V167='16' occurMaxTimes='1' minSize='-1' maxSize='-1' dataType='2' elemType='5' repHandlerStruct='' visible='true' inheritsFrom='' autoAddNew='true' V281='3' V1='4' name='55' description='Post Office Box' incarnation='1'>
      <structNode t='150' idref='1'/>
    </child>
    <child t='167' id='67' V167='16' occurMaxTimes='1' minSize='-1' maxSize='-1' dataType='2' elemType='5' repHandlerStruct='' visible='true' inheritsFrom='' autoAddNew='true' V281='3' V1='4' name='56' description='Division' incarnation='1'>
      <structNode t='150' idref='1'/>
    </child>
    <child t='167' id='68' V167='16' occurMaxTimes='1' minSize='-1' maxSize='-1' dataType='2' elemType='5' repHandlerStruct='' visible='true' inheritsFrom='' autoAddNew='true' V281='3' V1='4' name='57' description='Department' incarnation='1'>
      <structNode t='150' idref='1'/>
    </child>
    <child t='167' id='69' V167='16' occurMaxTimes='1' minSize='-1' maxSize='-1' dataType='2' elemType='5' repHandlerStruct='' visible='true' inheritsFrom='' autoAddNew='true' V281='3' V1='4' name='58' description='Originating Company Number' incarnation='1'>
      <structNode t='150' idref='1'/>
    </child>
    <child t='167' id='70' V167='16' occurMaxTimes='1' minSize='-1' maxSize='-1' dataType='2' elemType='5' repHandlerStruct='' visible='true' inheritsFrom='' autoAddNew='true' V281='3' V1='4' name='59' description='Receiving Company Number' incarnation='1'>
      <structNode t='150' idref='1'/>
    </child>
    <child t='167' id='71' V167='16' occurMaxTimes='1' minSize='-1' maxSize='-1' dataType='2' elemType='5' repHandlerStruct='' visible='true' inheritsFrom='' autoAddNew='true' V281='3' V1='4' name='61' description='Holding Mortgagee Number' incarnation='1'>
      <structNode t='150' idref='1'/>
    </child>
    <child t='167' id='72' V167='16' occurMaxTimes='1' minSize='-1' maxSize='-1' dataType='2' elemType='5' repHandlerStruct='' visible='true' inheritsFrom='' autoAddNew='true' V281='3' V1='4' name='62' description='Servicing Mortgagee Number' incarnation='1'>
      <structNode t='150' idref='1'/>
    </child>
    <child t='167' id='73' V167='16' occurMaxTimes='1' minSize='-1' maxSize='-1' dataType='2' elemType='5' repHandlerStruct='' visible='true' inheritsFrom='' autoAddNew='true' V281='3' V1='4' name='63' description='Servicer-holder Mortgagee Number' incarnation='1'>
      <structNode t='150' idref='1'/>
    </child>
    <child t='167' id='74' V167='16' occurMaxTimes='1' minSize='-1' maxSize='-1' dataType='2' elemType='5' repHandlerStruct='' visible='true' inheritsFrom='' autoAddNew='true' V281='3' V1='4' name='64' description='One Call Agency' incarnation='1'>
      <structNode t='150' idref='1'/>
    </child>
    <child t='167' id='75' V167='16' occurMaxTimes='1' minSize='-1' maxSize='-1' dataType='2' elemType='5' repHandlerStruct='' visible='true' inheritsFrom='' autoAddNew='true' V281='3' V1='4' name='71' description='Integrated Postsecondary Education Data System (IPEDS) set of codes maintained by the U.S. Department of Education&apos;s National Center of Education Statistics, Washington, D.C.' incarnation='1'>
      <structNode t='150' idref='1'/>
    </child>
    <child t='167' id='76' V167='16' occurMaxTimes='1' minSize='-1' maxSize='-1' dataType='2' elemType='5' repHandlerStruct='' visible='true' inheritsFrom='' autoAddNew='true' V281='3' V1='4' name='72' description='The College Board&apos;s Admission Testing Program (ATP), administered by the Educational Testing Service (ETS), 4-digit list of postsecondary educational institutions.' incarnation='1'>
      <structNode t='150' idref='1'/>
    </child>
    <child t='167' id='77' V167='16' occurMaxTimes='1' minSize='-1' maxSize='-1' dataType='2' elemType='5' repHandlerStruct='' visible='true' inheritsFrom='' autoAddNew='true' V281='3' V1='4' name='73' description='Federal Interagency Commission on Education (FICE) number. Available from the United States Department of Education, National Center for Education Statistics.' incarnation='1'>
      <structNode t='150' idref='1'/>
    </child>
    <child t='167' id='78' V167='16' occurMaxTimes='1' minSize='-1' maxSize='-1' dataType='2' elemType='5' repHandlerStruct='' visible='true' inheritsFrom='' autoAddNew='true' V281='3' V1='4' name='74' description='American College Testing (ACT) list of postsecondary educational institutions.' incarnation='1'>
      <structNode t='150' idref='1'/>
    </child>
    <child t='167' id='79' V167='16' occurMaxTimes='1' minSize='-1' maxSize='-1' dataType='2' elemType='5' repHandlerStruct='' visible='true' inheritsFrom='' autoAddNew='true' V281='3' V1='4' name='75' description='State or Province Assigned Number' incarnation='1'>
      <structNode t='150' idref='1'/>
    </child>
    <child t='167' id='80' V167='16' occurMaxTimes='1' minSize='-1' maxSize='-1' dataType='2' elemType='5' repHandlerStruct='' visible='true' inheritsFrom='' autoAddNew='true' V281='3' V1='4' name='76' description='Local School District or Jurisdiction Number' incarnation='1'>
      <structNode t='150' idref='1'/>
    </child>
    <child t='167' id='81' V167='16' occurMaxTimes='1' minSize='-1' maxSize='-1' dataType='2' elemType='5' repHandlerStruct='' visible='true' inheritsFrom='' autoAddNew='true' V281='3' V1='4' name='77' description='National Center for Education Statistics (NCES) Common Core of Data (CCD) number for PreK - 12 institutions' incarnation='1'>
      <structNode t='150' idref='1'/>
    </child>
    <child t='167' id='82' V167='16' occurMaxTimes='1' minSize='-1' maxSize='-1' dataType='2' elemType='5' repHandlerStruct='' visible='true' inheritsFrom='' autoAddNew='true' V281='3' V1='4' name='78' description='The College Board and ACT 6 digit code list of secondary educational institutions' incarnation='1'>
      <structNode t='150' idref='1'/>
    </child>
    <child t='167' id='83' V167='16' occurMaxTimes='1' minSize='-1' maxSize='-1' dataType='2' elemType='5' repHandlerStruct='' visible='true' inheritsFrom='' autoAddNew='true' V281='3' V1='4' name='81' description='Classification of Instructional Programs (CIP) coding structure maintained by the U.S. Department of Education&apos;s National Center for Education Statistics' incarnation='1'>
      <structNode t='150' idref='1'/>
    </child>
    <child t='167' id='84' V167='16' occurMaxTimes='1' minSize='-1' maxSize='-1' dataType='2' elemType='5' repHandlerStruct='' visible='true' inheritsFrom='' autoAddNew='true' V281='3' V1='4' name='82' description='Higher Education General Information Survey (HEGIS) maintained by the U.S. Department of Education&apos;s National Center for Education Statistics' incarnation='1'>
      <structNode t='150' idref='1'/>
    </child>
    <child t='167' id='85' V167='16' occurMaxTimes='1' minSize='-1' maxSize='-1' dataType='2' elemType='5' repHandlerStruct='' visible='true' inheritsFrom='' autoAddNew='true' V281='3' V1='4' name='90' description='California Ethnic Subgroups Code Table' incarnation='1'>
      <structNode t='150' idref='1'/>
    </child>
    <child t='167' id='86' V167='16' occurMaxTimes='1' minSize='-1' maxSize='-1' dataType='2' elemType='5' repHandlerStruct='' visible='true' inheritsFrom='' autoAddNew='true' V281='3' V1='4' name='91' description='Assigned by Seller or Seller&apos;s Agent' incarnation='1'>
      <structNode t='150' idref='1'/>
    </child>
    <child t='167' id='87' V167='16' occurMaxTimes='1' minSize='-1' maxSize='-1' dataType='2' elemType='5' repHandlerStruct='' visible='true' inheritsFrom='' autoAddNew='true' V281='3' V1='4' name='92' description='Assigned by Buyer or Buyer&apos;s Agent' incarnation='1'>
      <structNode t='150' idref='1'/>
    </child>
    <child t='167' id='88' V167='16' occurMaxTimes='1' minSize='-1' maxSize='-1' dataType='2' elemType='5' repHandlerStruct='' visible='true' inheritsFrom='' autoAddNew='true' V281='3' V1='4' name='93' description='Code assigned by the organization originating the transaction set' incarnation='1'>
      <structNode t='150' idref='1'/>
    </child>
    <child t='167' id='89' V167='16' occurMaxTimes='1' minSize='-1' maxSize='-1' dataType='2' elemType='5' repHandlerStruct='' visible='true' inheritsFrom='' autoAddNew='true' V281='3' V1='4' name='94' description='Code assigned by the organization that is the ultimate destination of the transaction set' incarnation='1'>
      <structNode t='150' idref='1'/>
    </child>
    <child t='167' id='90' V167='16' occurMaxTimes='1' minSize='-1' maxSize='-1' dataType='2' elemType='5' repHandlerStruct='' visible='true' inheritsFrom='' autoAddNew='true' V281='3' V1='4' name='95' description='Assigned By Transporter' incarnation='1'>
      <structNode t='150' idref='1'/>
    </child>
    <child t='167' id='91' V167='16' occurMaxTimes='1' minSize='-1' maxSize='-1' dataType='2' elemType='5' repHandlerStruct='' visible='true' inheritsFrom='' autoAddNew='true' V281='3' V1='4' name='96' description='Assigned By Pipeline Operator' incarnation='1'>
      <structNode t='150' idref='1'/>
    </child>
    <child t='167' id='92' V167='16' occurMaxTimes='1' minSize='-1' maxSize='-1' dataType='2' elemType='5' repHandlerStruct='' visible='true' inheritsFrom='' autoAddNew='true' V281='3' V1='4' name='97' description='Receiver&apos;s Code' incarnation='1'>
      <structNode t='150' idref='1'/>
    </child>
    <child t='167' id='93' V167='16' occurMaxTimes='1' minSize='-1' maxSize='-1' dataType='2' elemType='5' repHandlerStruct='' visible='true' inheritsFrom='' autoAddNew='true' V281='3' V1='4' name='98' description='Purchasing Office' incarnation='1'>
      <structNode t='150' idref='1'/>
    </child>
    <child t='167' id='94' V167='16' occurMaxTimes='1' minSize='-1' maxSize='-1' dataType='2' elemType='5' repHandlerStruct='' visible='true' inheritsFrom='' autoAddNew='true' V281='3' V1='4' name='99' description='Office of Workers Compensation Programs (OWCP) Agency Code' incarnation='1'>
      <structNode t='150' idref='1'/>
    </child>
    <child t='167' id='95' V167='16' occurMaxTimes='1' minSize='-1' maxSize='-1' dataType='2' elemType='5' repHandlerStruct='' visible='true' inheritsFrom='' autoAddNew='true' V281='3' V1='4' name='A1' description='Approver ID' incarnation='1'>
      <structNode t='150' idref='1'/>
    </child>
    <child t='167' id='96' V167='16' occurMaxTimes='1' minSize='-1' maxSize='-1' dataType='2' elemType='5' repHandlerStruct='' visible='true' inheritsFrom='' autoAddNew='true' V281='3' V1='4' name='A2' description='Military Assistance Program Address Code (MAPAC)' incarnation='1'>
      <structNode t='150' idref='1'/>
    </child>
    <child t='167' id='97' V167='16' occurMaxTimes='1' minSize='-1' maxSize='-1' dataType='2' elemType='5' repHandlerStruct='' visible='true' inheritsFrom='' autoAddNew='true' V281='3' V1='4' name='A3' description='Assigned by Third Party' incarnation='1'>
      <structNode t='150' idref='1'/>
    </child>
    <child t='167' id='98' V167='16' occurMaxTimes='1' minSize='-1' maxSize='-1' dataType='2' elemType='5' repHandlerStruct='' visible='true' inheritsFrom='' autoAddNew='true' V281='3' V1='4' name='A4' description='Assigned by Clearinghouse' incarnation='1'>
      <structNode t='150' idref='1'/>
    </child>
    <child t='167' id='99' V167='16' occurMaxTimes='1' minSize='-1' maxSize='-1' dataType='2' elemType='5' repHandlerStruct='' visible='true' inheritsFrom='' autoAddNew='true' V281='3' V1='4' name='A5' description='Committee on Uniform Security Identification Procedures (CUSIP) Number' incarnation='1'>
      <structNode t='150' idref='1'/>
    </child>
    <child t='167' id='100' V167='16' occurMaxTimes='1' minSize='-1' maxSize='-1' dataType='2' elemType='5' repHandlerStruct='' visible='true' inheritsFrom='' autoAddNew='true' V281='3' V1='4' name='A6' description='Financial Identification Numbering System (FINS) Number' incarnation='1'>
      <structNode t='150' idref='1'/>
    </child>
    <child t='167' id='101' V167='16' occurMaxTimes='1' minSize='-1' maxSize='-1' dataType='2' elemType='5' repHandlerStruct='' visible='true' inheritsFrom='' autoAddNew='true' V281='3' V1='4' name='AA' description='Postal Service Code' incarnation='1'>
      <structNode t='150' idref='1'/>
    </child>
    <child t='167' id='102' V167='16' occurMaxTimes='1' minSize='-1' maxSize='-1' dataType='2' elemType='5' repHandlerStruct='' visible='true' inheritsFrom='' autoAddNew='true' V281='3' V1='4' name='AB' description='US Environmental Protection Agency (EPA) Identification Number' incarnation='1'>
      <structNode t='150' idref='1'/>
    </child>
    <child t='167' id='103' V167='16' occurMaxTimes='1' minSize='-1' maxSize='-1' dataType='2' elemType='5' repHandlerStruct='' visible='true' inheritsFrom='' autoAddNew='true' V281='3' V1='4' name='AC' description='Attachment Control Number' incarnation='1'>
      <structNode t='150' idref='1'/>
    </child>
    <child t='167' id='104' V167='16' occurMaxTimes='1' minSize='-1' maxSize='-1' dataType='2' elemType='5' repHandlerStruct='' visible='true' inheritsFrom='' autoAddNew='true' V281='3' V1='4' name='AD' description='Blue Cross Blue Shield Association Plan Code' incarnation='1'>
      <structNode t='150' idref='1'/>
    </child>
    <child t='167' id='105' V167='16' occurMaxTimes='1' minSize='-1' maxSize='-1' dataType='2' elemType='5' repHandlerStruct='' visible='true' inheritsFrom='' autoAddNew='true' V281='3' V1='4' name='AE' description='Alberta Energy Resources Conservation Board' incarnation='1'>
      <structNode t='150' idref='1'/>
    </child>
    <child t='167' id='106' V167='16' occurMaxTimes='1' minSize='-1' maxSize='-1' dataType='2' elemType='5' repHandlerStruct='' visible='true' inheritsFrom='' autoAddNew='true' V281='3' V1='4' name='AF' description='Rental Location Identifier' incarnation='1'>
      <structNode t='150' idref='1'/>
    </child>
    <child t='167' id='107' V167='16' occurMaxTimes='1' minSize='-1' maxSize='-1' dataType='2' elemType='5' repHandlerStruct='' visible='true' inheritsFrom='' autoAddNew='true' V281='3' V1='4' name='AL' description='Anesthesia License Number' incarnation='1'>
      <structNode t='150' idref='1'/>
    </child>
    <child t='167' id='108' V167='16' occurMaxTimes='1' minSize='-1' maxSize='-1' dataType='2' elemType='5' repHandlerStruct='' visible='true' inheritsFrom='' autoAddNew='true' V281='3' V1='4' name='AP' description='Alberta Petroleum Marketing Commission' incarnation='1'>
      <structNode t='150' idref='1'/>
    </child>
    <child t='167' id='109' V167='16' occurMaxTimes='1' minSize='-1' maxSize='-1' dataType='2' elemType='5' repHandlerStruct='' visible='true' inheritsFrom='' autoAddNew='true' V281='3' V1='4' name='BC' description='British Columbia Ministry of Energy Mines and Petroleum Resources' incarnation='1'>
      <structNode t='150' idref='1'/>
    </child>
    <child t='167' id='110' V167='16' occurMaxTimes='1' minSize='-1' maxSize='-1' dataType='2' elemType='5' repHandlerStruct='' visible='true' inheritsFrom='' autoAddNew='true' V281='3' V1='4' name='BD' description='Blue Cross Provider Number' incarnation='1'>
      <structNode t='150' idref='1'/>
    </child>
    <child t='167' id='111' V167='16' occurMaxTimes='1' minSize='-1' maxSize='-1' dataType='2' elemType='5' repHandlerStruct='' visible='true' inheritsFrom='' autoAddNew='true' V281='3' V1='4' name='BE' description='Common Language Location Identification (CLLI)' incarnation='1'>
      <structNode t='150' idref='1'/>
    </child>
    <child t='167' id='112' V167='16' occurMaxTimes='1' minSize='-1' maxSize='-1' dataType='2' elemType='5' repHandlerStruct='' visible='true' inheritsFrom='' autoAddNew='true' V281='3' V1='4' name='BG' description='Badge Number' incarnation='1'>
      <structNode t='150' idref='1'/>
    </child>
    <child t='167' id='113' V167='16' occurMaxTimes='1' minSize='-1' maxSize='-1' dataType='2' elemType='5' repHandlerStruct='' visible='true' inheritsFrom='' autoAddNew='true' V281='3' V1='4' name='BP' description='Benefit Plan' incarnation='1'>
      <structNode t='150' idref='1'/>
    </child>
    <child t='167' id='114' V167='16' occurMaxTimes='1' minSize='-1' maxSize='-1' dataType='2' elemType='5' repHandlerStruct='' visible='true' inheritsFrom='' autoAddNew='true' V281='3' V1='4' name='BS' description='Blue Shield Provider Number' incarnation='1'>
      <structNode t='150' idref='1'/>
    </child>
    <child t='167' id='115' V167='16' occurMaxTimes='1' minSize='-1' maxSize='-1' dataType='2' elemType='5' repHandlerStruct='' visible='true' inheritsFrom='' autoAddNew='true' V281='3' V1='4' name='C1' description='Insured or Subscriber' incarnation='1'>
      <structNode t='150' idref='1'/>
    </child>
    <child t='167' id='116' V167='16' occurMaxTimes='1' minSize='-1' maxSize='-1' dataType='2' elemType='5' repHandlerStruct='' visible='true' inheritsFrom='' autoAddNew='true' V281='3' V1='4' name='C2' description='Health Maintenance Organization (HMO) Provider Number' incarnation='1'>
      <structNode t='150' idref='1'/>
    </child>
    <child t='167' id='117' V167='16' occurMaxTimes='1' minSize='-1' maxSize='-1' dataType='2' elemType='5' repHandlerStruct='' visible='true' inheritsFrom='' autoAddNew='true' V281='3' V1='4' name='C5' description='Customer Identification File' incarnation='1'>
      <structNode t='150' idref='1'/>
    </child>
    <child t='167' id='118' V167='16' occurMaxTimes='1' minSize='-1' maxSize='-1' dataType='2' elemType='5' repHandlerStruct='' visible='true' inheritsFrom='' autoAddNew='true' V281='3' V1='4' name='CA' description='Statistics Canada Canadian College Student Information System Course Codes' incarnation='1'>
      <structNode t='150' idref='1'/>
    </child>
    <child t='167' id='119' V167='16' occurMaxTimes='1' minSize='-1' maxSize='-1' dataType='2' elemType='5' repHandlerStruct='' visible='true' inheritsFrom='' autoAddNew='true' V281='3' V1='4' name='CB' description='Statistics Canada Canadian College Student Information System Institution Codes' incarnation='1'>
      <structNode t='150' idref='1'/>
    </child>
    <child t='167' id='120' V167='16' occurMaxTimes='1' minSize='-1' maxSize='-1' dataType='2' elemType='5' repHandlerStruct='' visible='true' inheritsFrom='' autoAddNew='true' V281='3' V1='4' name='CC' description='Statistics Canada University Student Information System Curriculum Codes' incarnation='1'>
      <structNode t='150' idref='1'/>
    </child>
    <child t='167' id='121' V167='16' occurMaxTimes='1' minSize='-1' maxSize='-1' dataType='2' elemType='5' repHandlerStruct='' visible='true' inheritsFrom='' autoAddNew='true' V281='3' V1='4' name='CD' description='Contract Division' incarnation='1'>
      <structNode t='150' idref='1'/>
    </child>
    <child t='167' id='122' V167='16' occurMaxTimes='1' minSize='-1' maxSize='-1' dataType='2' elemType='5' repHandlerStruct='' visible='true' inheritsFrom='' autoAddNew='true' V281='3' V1='4' name='CE' description='Bureau of the Census Filer Identification Code' incarnation='1'>
      <structNode t='150' idref='1'/>
    </child>
    <child t='167' id='123' V167='16' occurMaxTimes='1' minSize='-1' maxSize='-1' dataType='2' elemType='5' repHandlerStruct='' visible='true' inheritsFrom='' autoAddNew='true' V281='3' V1='4' name='CF' description='Canadian Financial Institution Routing Number' incarnation='1'>
      <structNode t='150' idref='1'/>
    </child>
    <child t='167' id='124' V167='16' occurMaxTimes='1' minSize='-1' maxSize='-1' dataType='2' elemType='5' repHandlerStruct='' visible='true' inheritsFrom='' autoAddNew='true' V281='3' V1='4' name='CI' description='CHAMPUS (Civilian Health and Medical Program of the Uniformed Services) Identification Number' incarnation='1'>
      <structNode t='150' idref='1'/>
    </child>
    <child t='167' id='125' V167='16' occurMaxTimes='1' minSize='-1' maxSize='-1' dataType='2' elemType='5' repHandlerStruct='' visible='true' inheritsFrom='' autoAddNew='true' V281='3' V1='4' name='CL' description='Corrected Loan Number' incarnation='1'>
      <structNode t='150' idref='1'/>
    </child>
    <child t='167' id='126' V167='16' occurMaxTimes='1' minSize='-1' maxSize='-1' dataType='2' elemType='5' repHandlerStruct='' visible='true' inheritsFrom='' autoAddNew='true' V281='3' V1='4' name='CM' description='U.S. Customs Service (USCS) Manufacturer Identifier (MID)' incarnation='1'>
      <structNode t='150' idref='1'/>
    </child>
    <child t='167' id='127' V167='16' occurMaxTimes='1' minSize='-1' maxSize='-1' dataType='2' elemType='5' repHandlerStruct='' visible='true' inheritsFrom='' autoAddNew='true' V281='3' V1='4' name='CP' description='Canadian Petroleum Association' incarnation='1'>
      <structNode t='150' idref='1'/>
    </child>
    <child t='167' id='128' V167='16' occurMaxTimes='1' minSize='-1' maxSize='-1' dataType='2' elemType='5' repHandlerStruct='' visible='true' inheritsFrom='' autoAddNew='true' V281='3' V1='4' name='CR' description='Credit Repository' incarnation='1'>
      <structNode t='150' idref='1'/>
    </child>
    <child t='167' id='129' V167='16' occurMaxTimes='1' minSize='-1' maxSize='-1' dataType='2' elemType='5' repHandlerStruct='' visible='true' inheritsFrom='' autoAddNew='true' V281='3' V1='4' name='CS' description='Statistics Canada University Student Information System University Codes' incarnation='1'>
      <structNode t='150' idref='1'/>
    </child>
    <child t='167' id='130' V167='16' occurMaxTimes='1' minSize='-1' maxSize='-1' dataType='2' elemType='5' repHandlerStruct='' visible='true' inheritsFrom='' autoAddNew='true' V281='3' V1='4' name='CT' description='Court Identification Code' incarnation='1'>
      <structNode t='150' idref='1'/>
    </child>
    <child t='167' id='131' V167='16' occurMaxTimes='1' minSize='-1' maxSize='-1' dataType='2' elemType='5' repHandlerStruct='' visible='true' inheritsFrom='' autoAddNew='true' V281='3' V1='4' name='DG' description='United States Department of Education Guarantor Identification Code' incarnation='1'>
      <structNode t='150' idref='1'/>
    </child>
    <child t='167' id='132' V167='16' occurMaxTimes='1' minSize='-1' maxSize='-1' dataType='2' elemType='5' repHandlerStruct='' visible='true' inheritsFrom='' autoAddNew='true' V281='3' V1='4' name='DL' description='United States Department of Education Lender Identification Code' incarnation='1'>
      <structNode t='150' idref='1'/>
    </child>
    <child t='167' id='133' V167='16' occurMaxTimes='1' minSize='-1' maxSize='-1' dataType='2' elemType='5' repHandlerStruct='' visible='true' inheritsFrom='' autoAddNew='true' V281='3' V1='4' name='DN' description='Dentist License Number' incarnation='1'>
      <structNode t='150' idref='1'/>
    </child>
    <child t='167' id='134' V167='16' occurMaxTimes='1' minSize='-1' maxSize='-1' dataType='2' elemType='5' repHandlerStruct='' visible='true' inheritsFrom='' autoAddNew='true' V281='3' V1='4' name='DP' description='Data Processing Point' incarnation='1'>
      <structNode t='150' idref='1'/>
    </child>
    <child t='167' id='135' V167='16' occurMaxTimes='1' minSize='-1' maxSize='-1' dataType='2' elemType='5' repHandlerStruct='' visible='true' inheritsFrom='' autoAddNew='true' V281='3' V1='4' name='DR' description='Gas Industry Standards Board (GISB) Data Reference Number (DRN)' incarnation='1'>
      <structNode t='150' idref='1'/>
    </child>
    <child t='167' id='136' V167='16' occurMaxTimes='1' minSize='-1' maxSize='-1' dataType='2' elemType='5' repHandlerStruct='' visible='true' inheritsFrom='' autoAddNew='true' V281='3' V1='4' name='DS' description='United States Department of Education School Identification Code' incarnation='1'>
      <structNode t='150' idref='1'/>
    </child>
    <child t='167' id='137' V167='16' occurMaxTimes='1' minSize='-1' maxSize='-1' dataType='2' elemType='5' repHandlerStruct='' visible='true' inheritsFrom='' autoAddNew='true' V281='3' V1='4' name='EC' description='ARI Electronic Commerce Location ID Code' incarnation='1'>
      <structNode t='150' idref='1'/>
    </child>
    <child t='167' id='138' V167='16' occurMaxTimes='1' minSize='-1' maxSize='-1' dataType='2' elemType='5' repHandlerStruct='' visible='true' inheritsFrom='' autoAddNew='true' V281='3' V1='4' name='EH' description='Theatre Number' incarnation='1'>
      <structNode t='150' idref='1'/>
    </child>
    <child t='167' id='139' V167='16' occurMaxTimes='1' minSize='-1' maxSize='-1' dataType='2' elemType='5' repHandlerStruct='' visible='true' inheritsFrom='' autoAddNew='true' V281='3' V1='4' name='EI' description='Employee Identification Number' incarnation='1'>
      <structNode t='150' idref='1'/>
    </child>
    <child t='167' id='140' V167='16' occurMaxTimes='1' minSize='-1' maxSize='-1' dataType='2' elemType='5' repHandlerStruct='' visible='true' inheritsFrom='' autoAddNew='true' V281='3' V1='4' name='EP' description='U.S. Environmental Protection Agency (EPA)' incarnation='1'>
      <structNode t='150' idref='1'/>
    </child>
    <child t='167' id='141' V167='16' occurMaxTimes='1' minSize='-1' maxSize='-1' dataType='2' elemType='5' repHandlerStruct='' visible='true' inheritsFrom='' autoAddNew='true' V281='3' V1='4' name='EQ' description='Insurance Company Assigned Identification Number' incarnation='1'>
      <structNode t='150' idref='1'/>
    </child>
    <child t='167' id='142' V167='16' occurMaxTimes='1' minSize='-1' maxSize='-1' dataType='2' elemType='5' repHandlerStruct='' visible='true' inheritsFrom='' autoAddNew='true' V281='3' V1='4' name='ER' description='Mortgagee Assigned Identification Number' incarnation='1'>
      <structNode t='150' idref='1'/>
    </child>
    <child t='167' id='143' V167='16' occurMaxTimes='1' minSize='-1' maxSize='-1' dataType='2' elemType='5' repHandlerStruct='' visible='true' inheritsFrom='' autoAddNew='true' V281='3' V1='4' name='ES' description='Automated Export System (AES) Filer Identification Code' incarnation='1'>
      <structNode t='150' idref='1'/>
    </child>
    <child t='167' id='144' V167='16' occurMaxTimes='1' minSize='-1' maxSize='-1' dataType='2' elemType='5' repHandlerStruct='' visible='true' inheritsFrom='' autoAddNew='true' V281='3' V1='4' name='ET' description='Educational Testing Service List of International Postsecondary Institutions' incarnation='1'>
      <structNode t='150' idref='1'/>
    </child>
    <child t='167' id='145' V167='16' occurMaxTimes='1' minSize='-1' maxSize='-1' dataType='2' elemType='5' repHandlerStruct='' visible='true' inheritsFrom='' autoAddNew='true' V281='3' V1='4' name='FA' description='Facility Identification' incarnation='1'>
      <structNode t='150' idref='1'/>
    </child>
    <child t='167' id='146' V167='16' occurMaxTimes='1' minSize='-1' maxSize='-1' dataType='2' elemType='5' repHandlerStruct='' visible='true' inheritsFrom='' autoAddNew='true' V281='3' V1='4' name='FB' description='Field Code' incarnation='1'>
      <structNode t='150' idref='1'/>
    </child>
    <child t='167' id='147' V167='16' occurMaxTimes='1' minSize='-1' maxSize='-1' dataType='2' elemType='5' repHandlerStruct='' visible='true' inheritsFrom='' autoAddNew='true' V281='3' V1='4' name='FC' description='Federal Court Jurisdiction Identifier' incarnation='1'>
      <structNode t='150' idref='1'/>
    </child>
    <child t='167' id='148' V167='16' occurMaxTimes='1' minSize='-1' maxSize='-1' dataType='2' elemType='5' repHandlerStruct='' visible='true' inheritsFrom='' autoAddNew='true' V281='3' V1='4' name='FD' description='Federal Court Divisional Office Number' incarnation='1'>
      <structNode t='150' idref='1'/>
    </child>
    <child t='167' id='149' V167='16' occurMaxTimes='1' minSize='-1' maxSize='-1' dataType='2' elemType='5' repHandlerStruct='' visible='true' inheritsFrom='' autoAddNew='true' V281='3' V1='4' name='FI' description='Federal Taxpayer&apos;s Identification Number' incarnation='1'>
      <structNode t='150' idref='1'/>
    </child>
    <child t='167' id='150' V167='16' occurMaxTimes='1' minSize='-1' maxSize='-1' dataType='2' elemType='5' repHandlerStruct='' visible='true' inheritsFrom='' autoAddNew='true' V281='3' V1='4' name='FJ' description='Federal Jurisdiction' incarnation='1'>
      <structNode t='150' idref='1'/>
    </child>
    <child t='167' id='151' V167='16' occurMaxTimes='1' minSize='-1' maxSize='-1' dataType='2' elemType='5' repHandlerStruct='' visible='true' inheritsFrom='' autoAddNew='true' V281='3' V1='4' name='FN' description='U.S. Environmental Protection Agency (EPA) Laboratory Certification Identification' incarnation='1'>
      <structNode t='150' idref='1'/>
    </child>
    <child t='167' id='152' V167='16' occurMaxTimes='1' minSize='-1' maxSize='-1' dataType='2' elemType='5' repHandlerStruct='' visible='true' inheritsFrom='' autoAddNew='true' V281='3' V1='4' name='GA' description='Primary Agent Identification' incarnation='1'>
      <structNode t='150' idref='1'/>
    </child>
    <child t='167' id='153' V167='16' occurMaxTimes='1' minSize='-1' maxSize='-1' dataType='2' elemType='5' repHandlerStruct='' visible='true' inheritsFrom='' autoAddNew='true' V281='3' V1='4' name='GC' description='GAS*CODE' incarnation='1'>
      <structNode t='150' idref='1'/>
    </child>
    <child t='167' id='154' V167='16' occurMaxTimes='1' minSize='-1' maxSize='-1' dataType='2' elemType='5' repHandlerStruct='' visible='true' inheritsFrom='' autoAddNew='true' V281='3' V1='4' name='HC' description='Health Care Financing Administration' incarnation='1'>
      <structNode t='150' idref='1'/>
    </child>
    <child t='167' id='155' V167='16' occurMaxTimes='1' minSize='-1' maxSize='-1' dataType='2' elemType='5' repHandlerStruct='' visible='true' inheritsFrom='' autoAddNew='true' V281='3' V1='4' name='HN' description='Health Insurance Claim (HIC) Number' incarnation='1'>
      <structNode t='150' idref='1'/>
    </child>
    <child t='167' id='156' V167='16' occurMaxTimes='1' minSize='-1' maxSize='-1' dataType='2' elemType='5' repHandlerStruct='' visible='true' inheritsFrom='' autoAddNew='true' V281='3' V1='4' name='II' description='Standard Unique Health Identifier for each Individual in the United States' incarnation='1'>
      <structNode t='150' idref='1'/>
    </child>
    <child t='167' id='157' V167='16' occurMaxTimes='1' minSize='-1' maxSize='-1' dataType='2' elemType='5' repHandlerStruct='' visible='true' inheritsFrom='' autoAddNew='true' V281='3' V1='4' name='LC' description='Agency Location Code (U.S. Government)' incarnation='1'>
      <structNode t='150' idref='1'/>
    </child>
    <child t='167' id='158' V167='16' occurMaxTimes='1' minSize='-1' maxSize='-1' dataType='2' elemType='5' repHandlerStruct='' visible='true' inheritsFrom='' autoAddNew='true' V281='3' V1='4' name='LD' description='NISO Z39.53 Language Codes' incarnation='1'>
      <structNode t='150' idref='1'/>
    </child>
    <child t='167' id='159' V167='16' occurMaxTimes='1' minSize='-1' maxSize='-1' dataType='2' elemType='5' repHandlerStruct='' visible='true' inheritsFrom='' autoAddNew='true' V281='3' V1='4' name='LE' description='ISO 639 Language Codes' incarnation='1'>
      <structNode t='150' idref='1'/>
    </child>
    <child t='167' id='160' V167='16' occurMaxTimes='1' minSize='-1' maxSize='-1' dataType='2' elemType='5' repHandlerStruct='' visible='true' inheritsFrom='' autoAddNew='true' V281='3' V1='4' name='LI' description='Labeler Identification Code (LIC)' incarnation='1'>
      <structNode t='150' idref='1'/>
    </child>
    <child t='167' id='161' V167='16' occurMaxTimes='1' minSize='-1' maxSize='-1' dataType='2' elemType='5' repHandlerStruct='' visible='true' inheritsFrom='' autoAddNew='true' V281='3' V1='4' name='LN' description='Loan Number' incarnation='1'>
      <structNode t='150' idref='1'/>
    </child>
    <child t='167' id='162' V167='16' occurMaxTimes='1' minSize='-1' maxSize='-1' dataType='2' elemType='5' repHandlerStruct='' visible='true' inheritsFrom='' autoAddNew='true' V281='3' V1='4' name='M3' description='Disbursing Station' incarnation='1'>
      <structNode t='150' idref='1'/>
    </child>
    <child t='167' id='163' V167='16' occurMaxTimes='1' minSize='-1' maxSize='-1' dataType='2' elemType='5' repHandlerStruct='' visible='true' inheritsFrom='' autoAddNew='true' V281='3' V1='4' name='M4' description='Department of Defense Routing Identifier Code (RIC)' incarnation='1'>
      <structNode t='150' idref='1'/>
    </child>
    <child t='167' id='164' V167='16' occurMaxTimes='1' minSize='-1' maxSize='-1' dataType='2' elemType='5' repHandlerStruct='' visible='true' inheritsFrom='' autoAddNew='true' V281='3' V1='4' name='M5' description='Jurisdiction Code' incarnation='1'>
      <structNode t='150' idref='1'/>
    </child>
    <child t='167' id='165' V167='16' occurMaxTimes='1' minSize='-1' maxSize='-1' dataType='2' elemType='5' repHandlerStruct='' visible='true' inheritsFrom='' autoAddNew='true' V281='3' V1='4' name='M6' description='Division Office Code' incarnation='1'>
      <structNode t='150' idref='1'/>
    </child>
    <child t='167' id='166' V167='16' occurMaxTimes='1' minSize='-1' maxSize='-1' dataType='2' elemType='5' repHandlerStruct='' visible='true' inheritsFrom='' autoAddNew='true' V281='3' V1='4' name='MA' description='Mail Stop' incarnation='1'>
      <structNode t='150' idref='1'/>
    </child>
    <child t='167' id='167' V167='16' occurMaxTimes='1' minSize='-1' maxSize='-1' dataType='2' elemType='5' repHandlerStruct='' visible='true' inheritsFrom='' autoAddNew='true' V281='3' V1='4' name='MB' description='Medical Information Bureau' incarnation='1'>
      <structNode t='150' idref='1'/>
    </child>
    <child t='167' id='168' V167='16' occurMaxTimes='1' minSize='-1' maxSize='-1' dataType='2' elemType='5' repHandlerStruct='' visible='true' inheritsFrom='' autoAddNew='true' V281='3' V1='4' name='MC' description='Medicaid Provider Number' incarnation='1'>
      <structNode t='150' idref='1'/>
    </child>
    <child t='167' id='169' V167='16' occurMaxTimes='1' minSize='-1' maxSize='-1' dataType='2' elemType='5' repHandlerStruct='' visible='true' inheritsFrom='' autoAddNew='true' V281='3' V1='4' name='MD' description='Manitoba Department of Mines and Resources' incarnation='1'>
      <structNode t='150' idref='1'/>
    </child>
    <child t='167' id='170' V167='16' occurMaxTimes='1' minSize='-1' maxSize='-1' dataType='2' elemType='5' repHandlerStruct='' visible='true' inheritsFrom='' autoAddNew='true' V281='3' V1='4' name='MI' description='Member Identification Number' incarnation='1'>
      <structNode t='150' idref='1'/>
    </child>
    <child t='167' id='171' V167='16' occurMaxTimes='1' minSize='-1' maxSize='-1' dataType='2' elemType='5' repHandlerStruct='' visible='true' inheritsFrom='' autoAddNew='true' V281='3' V1='4' name='MK' description='Market' incarnation='1'>
      <structNode t='150' idref='1'/>
    </child>
    <child t='167' id='172' V167='16' occurMaxTimes='1' minSize='-1' maxSize='-1' dataType='2' elemType='5' repHandlerStruct='' visible='true' inheritsFrom='' autoAddNew='true' V281='3' V1='4' name='ML' description='Multiple Listing Service Vendor - Multiple Listing Service Identification' incarnation='1'>
      <structNode t='150' idref='1'/>
    </child>
    <child t='167' id='173' V167='16' occurMaxTimes='1' minSize='-1' maxSize='-1' dataType='2' elemType='5' repHandlerStruct='' visible='true' inheritsFrom='' autoAddNew='true' V281='3' V1='4' name='MN' description='Mortgage Identification Number' incarnation='1'>
      <structNode t='150' idref='1'/>
    </child>
    <child t='167' id='174' V167='16' occurMaxTimes='1' minSize='-1' maxSize='-1' dataType='2' elemType='5' repHandlerStruct='' visible='true' inheritsFrom='' autoAddNew='true' V281='3' V1='4' name='MP' description='Medicare Provider Number' incarnation='1'>
      <structNode t='150' idref='1'/>
    </child>
    <child t='167' id='175' V167='16' occurMaxTimes='1' minSize='-1' maxSize='-1' dataType='2' elemType='5' repHandlerStruct='' visible='true' inheritsFrom='' autoAddNew='true' V281='3' V1='4' name='MR' description='Medicaid Recipient Identification Number' incarnation='1'>
      <structNode t='150' idref='1'/>
    </child>
    <child t='167' id='176' V167='16' occurMaxTimes='1' minSize='-1' maxSize='-1' dataType='2' elemType='5' repHandlerStruct='' visible='true' inheritsFrom='' autoAddNew='true' V281='3' V1='4' name='NA' description='National Association of Realtors - Multiple Listing Service Identification' incarnation='1'>
      <structNode t='150' idref='1'/>
    </child>
    <child t='167' id='177' V167='16' occurMaxTimes='1' minSize='-1' maxSize='-1' dataType='2' elemType='5' repHandlerStruct='' visible='true' inheritsFrom='' autoAddNew='true' V281='3' V1='4' name='ND' description='Mode Designator' incarnation='1'>
      <structNode t='150' idref='1'/>
    </child>
    <child t='167' id='178' V167='16' occurMaxTimes='1' minSize='-1' maxSize='-1' dataType='2' elemType='5' repHandlerStruct='' visible='true' inheritsFrom='' autoAddNew='true' V281='3' V1='4' name='NI' description='National Association of Insurance Commissioners (NAIC) Identification' incarnation='1'>
      <structNode t='150' idref='1'/>
    </child>
    <child t='167' id='179' V167='16' occurMaxTimes='1' minSize='-1' maxSize='-1' dataType='2' elemType='5' repHandlerStruct='' visible='true' inheritsFrom='' autoAddNew='true' V281='3' V1='4' name='NO' description='National Criminal Information Center Originating Agency' incarnation='1'>
      <structNode t='150' idref='1'/>
    </child>
    <child t='167' id='180' V167='16' occurMaxTimes='1' minSize='-1' maxSize='-1' dataType='2' elemType='5' repHandlerStruct='' visible='true' inheritsFrom='' autoAddNew='true' V281='3' V1='4' name='NR' description='Non Resident Alien Registration Number' incarnation='1'>
      <structNode t='150' idref='1'/>
    </child>
    <child t='167' id='181' V167='16' occurMaxTimes='1' minSize='-1' maxSize='-1' dataType='2' elemType='5' repHandlerStruct='' visible='true' inheritsFrom='' autoAddNew='true' V281='3' V1='4' name='OC' description='Occupation Code' incarnation='1'>
      <structNode t='150' idref='1'/>
    </child>
    <child t='167' id='182' V167='16' occurMaxTimes='1' minSize='-1' maxSize='-1' dataType='2' elemType='5' repHandlerStruct='' visible='true' inheritsFrom='' autoAddNew='true' V281='3' V1='4' name='OP' description='On-line Payment and Collection' incarnation='1'>
      <structNode t='150' idref='1'/>
    </child>
    <child t='167' id='183' V167='16' occurMaxTimes='1' minSize='-1' maxSize='-1' dataType='2' elemType='5' repHandlerStruct='' visible='true' inheritsFrom='' autoAddNew='true' V281='3' V1='4' name='PA' description='Secondary Agent Identification' incarnation='1'>
      <structNode t='150' idref='1'/>
    </child>
    <child t='167' id='184' V167='16' occurMaxTimes='1' minSize='-1' maxSize='-1' dataType='2' elemType='5' repHandlerStruct='' visible='true' inheritsFrom='' autoAddNew='true' V281='3' V1='4' name='PB' description='Public Identification' incarnation='1'>
      <structNode t='150' idref='1'/>
    </child>
    <child t='167' id='185' V167='16' occurMaxTimes='1' minSize='-1' maxSize='-1' dataType='2' elemType='5' repHandlerStruct='' visible='true' inheritsFrom='' autoAddNew='true' V281='3' V1='4' name='PC' description='Provider Commercial Number' incarnation='1'>
      <structNode t='150' idref='1'/>
    </child>
    <child t='167' id='186' V167='16' occurMaxTimes='1' minSize='-1' maxSize='-1' dataType='2' elemType='5' repHandlerStruct='' visible='true' inheritsFrom='' autoAddNew='true' V281='3' V1='4' name='PI' description='Payor Identification' incarnation='1'>
      <structNode t='150' idref='1'/>
    </child>
    <child t='167' id='187' V167='16' occurMaxTimes='1' minSize='-1' maxSize='-1' dataType='2' elemType='5' repHandlerStruct='' visible='true' inheritsFrom='' autoAddNew='true' V281='3' V1='4' name='PP' description='Pharmacy Processor Number' incarnation='1'>
      <structNode t='150' idref='1'/>
    </child>
    <child t='167' id='188' V167='16' occurMaxTimes='1' minSize='-1' maxSize='-1' dataType='2' elemType='5' repHandlerStruct='' visible='true' inheritsFrom='' autoAddNew='true' V281='3' V1='4' name='PR' description='Pier' incarnation='1'>
      <structNode t='150' idref='1'/>
    </child>
    <child t='167' id='189' V167='16' occurMaxTimes='1' minSize='-1' maxSize='-1' dataType='2' elemType='5' repHandlerStruct='' visible='true' inheritsFrom='' autoAddNew='true' V281='3' V1='4' name='RA' description='Regulatory Agency Number' incarnation='1'>
      <structNode t='150' idref='1'/>
    </child>
    <child t='167' id='190' V167='16' occurMaxTimes='1' minSize='-1' maxSize='-1' dataType='2' elemType='5' repHandlerStruct='' visible='true' inheritsFrom='' autoAddNew='true' V281='3' V1='4' name='RB' description='Real Estate Agent' incarnation='1'>
      <structNode t='150' idref='1'/>
    </child>
    <child t='167' id='191' V167='16' occurMaxTimes='1' minSize='-1' maxSize='-1' dataType='2' elemType='5' repHandlerStruct='' visible='true' inheritsFrom='' autoAddNew='true' V281='3' V1='4' name='RC' description='Real Estate Company' incarnation='1'>
      <structNode t='150' idref='1'/>
    </child>
    <child t='167' id='192' V167='16' occurMaxTimes='1' minSize='-1' maxSize='-1' dataType='2' elemType='5' repHandlerStruct='' visible='true' inheritsFrom='' autoAddNew='true' V281='3' V1='4' name='RD' description='Real Estate Broker Identification' incarnation='1'>
      <structNode t='150' idref='1'/>
    </child>
    <child t='167' id='193' V167='16' occurMaxTimes='1' minSize='-1' maxSize='-1' dataType='2' elemType='5' repHandlerStruct='' visible='true' inheritsFrom='' autoAddNew='true' V281='3' V1='4' name='RE' description='Real Estate License Number' incarnation='1'>
      <structNode t='150' idref='1'/>
    </child>
    <child t='167' id='194' V167='16' occurMaxTimes='1' minSize='-1' maxSize='-1' dataType='2' elemType='5' repHandlerStruct='' visible='true' inheritsFrom='' autoAddNew='true' V281='3' V1='4' name='RT' description='Railroad Track' incarnation='1'>
      <structNode t='150' idref='1'/>
    </child>
    <child t='167' id='195' V167='16' occurMaxTimes='1' minSize='-1' maxSize='-1' dataType='2' elemType='5' repHandlerStruct='' visible='true' inheritsFrom='' autoAddNew='true' V281='3' V1='4' name='SA' description='Tertiary Agent Identification' incarnation='1'>
      <structNode t='150' idref='1'/>
    </child>
    <child t='167' id='196' V167='16' occurMaxTimes='1' minSize='-1' maxSize='-1' dataType='2' elemType='5' repHandlerStruct='' visible='true' inheritsFrom='' autoAddNew='true' V281='3' V1='4' name='SB' description='Social Insurance Number' incarnation='1'>
      <structNode t='150' idref='1'/>
    </child>
    <child t='167' id='197' V167='16' occurMaxTimes='1' minSize='-1' maxSize='-1' dataType='2' elemType='5' repHandlerStruct='' visible='true' inheritsFrom='' autoAddNew='true' V281='3' V1='4' name='SD' description='Saskatchewan Department of Energy Mines and Resources' incarnation='1'>
      <structNode t='150' idref='1'/>
    </child>
    <child t='167' id='198' V167='16' occurMaxTimes='1' minSize='-1' maxSize='-1' dataType='2' elemType='5' repHandlerStruct='' visible='true' inheritsFrom='' autoAddNew='true' V281='3' V1='4' name='SF' description='Suffix Code' incarnation='1'>
      <structNode t='150' idref='1'/>
    </child>
    <child t='167' id='199' V167='16' occurMaxTimes='1' minSize='-1' maxSize='-1' dataType='2' elemType='5' repHandlerStruct='' visible='true' inheritsFrom='' autoAddNew='true' V281='3' V1='4' name='SI' description='Standard Industry Code (SIC)' incarnation='1'>
      <structNode t='150' idref='1'/>
    </child>
    <child t='167' id='200' V167='16' occurMaxTimes='1' minSize='-1' maxSize='-1' dataType='2' elemType='5' repHandlerStruct='' visible='true' inheritsFrom='' autoAddNew='true' V281='3' V1='4' name='SJ' description='State Jurisdiction' incarnation='1'>
      <structNode t='150' idref='1'/>
    </child>
    <child t='167' id='201' V167='16' occurMaxTimes='1' minSize='-1' maxSize='-1' dataType='2' elemType='5' repHandlerStruct='' visible='true' inheritsFrom='' autoAddNew='true' V281='3' V1='4' name='SK' description='State/Provincial Lottery License Number' incarnation='1'>
      <structNode t='150' idref='1'/>
    </child>
    <child t='167' id='202' V167='16' occurMaxTimes='1' minSize='-1' maxSize='-1' dataType='2' elemType='5' repHandlerStruct='' visible='true' inheritsFrom='' autoAddNew='true' V281='3' V1='4' name='SL' description='State License Number' incarnation='1'>
      <structNode t='150' idref='1'/>
    </child>
    <child t='167' id='203' V167='16' occurMaxTimes='1' minSize='-1' maxSize='-1' dataType='2' elemType='5' repHandlerStruct='' visible='true' inheritsFrom='' autoAddNew='true' V281='3' V1='4' name='SP' description='Specialty License Number' incarnation='1'>
      <structNode t='150' idref='1'/>
    </child>
    <child t='167' id='204' V167='16' occurMaxTimes='1' minSize='-1' maxSize='-1' dataType='2' elemType='5' repHandlerStruct='' visible='true' inheritsFrom='' autoAddNew='true' V281='3' V1='4' name='ST' description='State/Province License Tag' incarnation='1'>
      <structNode t='150' idref='1'/>
    </child>
    <child t='167' id='205' V167='16' occurMaxTimes='1' minSize='-1' maxSize='-1' dataType='2' elemType='5' repHandlerStruct='' visible='true' inheritsFrom='' autoAddNew='true' V281='3' V1='4' name='SV' description='Service Provider Number' incarnation='1'>
      <structNode t='150' idref='1'/>
    </child>
    <child t='167' id='206' V167='16' occurMaxTimes='1' minSize='-1' maxSize='-1' dataType='2' elemType='5' repHandlerStruct='' visible='true' inheritsFrom='' autoAddNew='true' V281='3' V1='4' name='SW' description='Society for Worldwide Interbank Financial Telecommunications (SWIFT) Address' incarnation='1'>
      <structNode t='150' idref='1'/>
    </child>
    <child t='167' id='207' V167='16' occurMaxTimes='1' minSize='-1' maxSize='-1' dataType='2' elemType='5' repHandlerStruct='' visible='true' inheritsFrom='' autoAddNew='true' V281='3' V1='4' name='TA' description='Taxpayer ID Number' incarnation='1'>
      <structNode t='150' idref='1'/>
    </child>
    <child t='167' id='208' V167='16' occurMaxTimes='1' minSize='-1' maxSize='-1' dataType='2' elemType='5' repHandlerStruct='' visible='true' inheritsFrom='' autoAddNew='true' V281='3' V1='4' name='TC' description='Internal Revenue Service Terminal Code' incarnation='1'>
      <structNode t='150' idref='1'/>
    </child>
    <child t='167' id='209' V167='16' occurMaxTimes='1' minSize='-1' maxSize='-1' dataType='2' elemType='5' repHandlerStruct='' visible='true' inheritsFrom='' autoAddNew='true' V281='3' V1='4' name='TL' description='Transport4 Location Code' incarnation='1'>
      <structNode t='150' idref='1'/>
    </child>
    <child t='167' id='210' V167='16' occurMaxTimes='1' minSize='-1' maxSize='-1' dataType='2' elemType='5' repHandlerStruct='' visible='true' inheritsFrom='' autoAddNew='true' V281='3' V1='4' name='TS' description='Transport4 Shipper Code' incarnation='1'>
      <structNode t='150' idref='1'/>
    </child>
    <child t='167' id='211' V167='16' occurMaxTimes='1' minSize='-1' maxSize='-1' dataType='2' elemType='5' repHandlerStruct='' visible='true' inheritsFrom='' autoAddNew='true' V281='3' V1='4' name='TZ' description='Department Code' incarnation='1'>
      <structNode t='150' idref='1'/>
    </child>
    <child t='167' id='212' V167='16' occurMaxTimes='1' minSize='-1' maxSize='-1' dataType='2' elemType='5' repHandlerStruct='' visible='true' inheritsFrom='' autoAddNew='true' V281='3' V1='4' name='UC' description='Consumer Credit Identification Number' incarnation='1'>
      <structNode t='150' idref='1'/>
    </child>
    <child t='167' id='213' V167='16' occurMaxTimes='1' minSize='-1' maxSize='-1' dataType='2' elemType='5' repHandlerStruct='' visible='true' inheritsFrom='' autoAddNew='true' V281='3' V1='4' name='UL' description='UCC/EAN Location Code' incarnation='1'>
      <structNode t='150' idref='1'/>
    </child>
    <child t='167' id='214' V167='16' occurMaxTimes='1' minSize='-1' maxSize='-1' dataType='2' elemType='5' repHandlerStruct='' visible='true' inheritsFrom='' autoAddNew='true' V281='3' V1='4' name='UM' description='UCC/EAN Location Code Suffix' incarnation='1'>
      <structNode t='150' idref='1'/>
    </child>
    <child t='167' id='215' V167='16' occurMaxTimes='1' minSize='-1' maxSize='-1' dataType='2' elemType='5' repHandlerStruct='' visible='true' inheritsFrom='' autoAddNew='true' V281='3' V1='4' name='UP' description='Unique Physician Identification Number (UPIN)' incarnation='1'>
      <structNode t='150' idref='1'/>
    </child>
    <child t='167' id='216' V167='16' occurMaxTimes='1' minSize='-1' maxSize='-1' dataType='2' elemType='5' repHandlerStruct='' visible='true' inheritsFrom='' autoAddNew='true' V281='3' V1='4' name='UR' description='Uniform Resource Locator (URL)' incarnation='1'>
      <structNode t='150' idref='1'/>
    </child>
    <child t='167' id='217' V167='16' occurMaxTimes='1' minSize='-1' maxSize='-1' dataType='2' elemType='5' repHandlerStruct='' visible='true' inheritsFrom='' autoAddNew='true' V281='3' V1='4' name='US' description='Unique Supplier Identification Number (USIN)' incarnation='1'>
      <structNode t='150' idref='1'/>
    </child>
    <child t='167' id='218' V167='16' occurMaxTimes='1' minSize='-1' maxSize='-1' dataType='2' elemType='5' repHandlerStruct='' visible='true' inheritsFrom='' autoAddNew='true' V281='3' V1='4' name='WR' description='Wine Region Code' incarnation='1'>
      <structNode t='150' idref='1'/>
    </child>
    <child t='167' id='219' V167='16' occurMaxTimes='1' minSize='-1' maxSize='-1' dataType='2' elemType='5' repHandlerStruct='' visible='true' inheritsFrom='' autoAddNew='true' V281='3' V1='4' name='WS' description='Education Language Codes' incarnation='1'>
      <structNode t='150' idref='1'/>
    </child>
    <child t='167' id='220' V167='16' occurMaxTimes='1' minSize='-1' maxSize='-1' dataType='2' elemType='5' repHandlerStruct='' visible='true' inheritsFrom='' autoAddNew='true' V281='3' V1='4' name='XV' description='Health Care Financing Administration National Payer Identification Number (PAYERID)' incarnation='1'>
      <structNode t='150' idref='1'/>
    </child>
    <child t='167' id='221' V167='16' occurMaxTimes='1' minSize='-1' maxSize='-1' dataType='2' elemType='5' repHandlerStruct='' visible='true' inheritsFrom='' autoAddNew='true' V281='3' V1='4' name='XX' description='Health Care Financing Administration National Provider Identifier' incarnation='1'>
      <structNode t='150' idref='1'/>
    </child>
    <child t='167' id='222' V167='16' occurMaxTimes='1' minSize='-1' maxSize='-1' dataType='2' elemType='5' repHandlerStruct='' visible='true' inheritsFrom='' autoAddNew='true' V281='3' V1='4' name='ZC' description='Contractor Establishment Code' incarnation='1'>
      <structNode t='150' idref='1'/>
    </child>
    <child t='167' id='223' V167='16' occurMaxTimes='1' minSize='-1' maxSize='-1' dataType='2' elemType='5' repHandlerStruct='' visible='true' inheritsFrom='' autoAddNew='true' V281='3' V1='4' name='ZN' description='Zone' incarnation='1'>
      <structNode t='150' idref='1'/>
    </child>
    <child t='167' id='224' V167='16' occurMaxTimes='1' minSize='-1' maxSize='-1' dataType='2' elemType='5' repHandlerStruct='' visible='true' inheritsFrom='' autoAddNew='true' V281='3' V1='4' name='ZY' description='Temporary Identification Number' incarnation='1'>
      <structNode t='150' idref='1'/>
    </child>
    <child t='167' id='225' V167='16' occurMaxTimes='1' minSize='-1' maxSize='-1' dataType='2' elemType='5' repHandlerStruct='' visible='true' inheritsFrom='' autoAddNew='true' V281='3' V1='4' name='ZZ' description='Mutually Defined' incarnation='1'>
      <structNode t='150' idref='1'/>
    </child>
  </rootElem>
  <child t='162' id='226' V1='4' name='Representations' incarnation='1'>
  </child>
  <child t='165' id='227' V1='4' name='Document Bindings' incarnation='1'>
  </child>
</root>
