<?xml version="1.0" ?>
<root t='150' id='1' V150='12' creationTimestamp='0x11d4271f81f' V1='4' name='I05' incarnation='6'>
  <rootElem t='167' id='2' V167='16' occurMaxTimes='1' minSize='2' maxSize='2' dataType='2' ediElemType='5' ediElemRef='I05' repHandlerStruct='' visible='true' nullable='true' inheritsFrom='' inheritsFromCopyRule='16' needInheritInit='true' V281='3' V1='4' name='EI05'>
    <structNode t='150' idref='1'/>
    <purpose>Code indicating the system/method of code structure used to designate the sender or receiver ID element being qualified</purpose>
    <child t='167' id='3' V167='16' occurMaxTimes='1' minSize='-1' maxSize='-1' dataType='2' elemType='5' repHandlerStruct='' visible='true' inheritsFrom='' autoAddNew='true' V281='3' V1='4' name='01' description='Duns (Dun &amp; Bradstreet)' incarnation='1'>
      <structNode t='150' idref='1'/>
    </child>
    <child t='167' id='4' V167='16' occurMaxTimes='1' minSize='-1' maxSize='-1' dataType='2' elemType='5' repHandlerStruct='' visible='true' inheritsFrom='' autoAddNew='true' V281='3' V1='4' name='02' description='SCAC (Standard Carrier Alpha Code)' incarnation='1'>
      <structNode t='150' idref='1'/>
    </child>
    <child t='167' id='5' V167='16' occurMaxTimes='1' minSize='-1' maxSize='-1' dataType='2' elemType='5' repHandlerStruct='' visible='true' inheritsFrom='' autoAddNew='true' V281='3' V1='4' name='03' description='FMC (Federal Maritime Commission)' incarnation='1'>
      <structNode t='150' idref='1'/>
    </child>
    <child t='167' id='6' V167='16' occurMaxTimes='1' minSize='-1' maxSize='-1' dataType='2' elemType='5' repHandlerStruct='' visible='true' inheritsFrom='' autoAddNew='true' V281='3' V1='4' name='04' description='IATA (International Air Transport Association)' incarnation='1'>
      <structNode t='150' idref='1'/>
    </child>
    <child t='167' id='7' V167='16' occurMaxTimes='1' minSize='-1' maxSize='-1' dataType='2' elemType='5' repHandlerStruct='' visible='true' inheritsFrom='' autoAddNew='true' V281='3' V1='4' name='07' description='UCC/EAN Location Code' incarnation='1'>
      <structNode t='150' idref='1'/>
    </child>
    <child t='167' id='8' V167='16' occurMaxTimes='1' minSize='-1' maxSize='-1' dataType='2' elemType='5' repHandlerStruct='' visible='true' inheritsFrom='' autoAddNew='true' V281='3' V1='4' name='08' description='UCC EDI Communications ID (Comm ID)' incarnation='1'>
      <structNode t='150' idref='1'/>
    </child>
    <child t='167' id='9' V167='16' occurMaxTimes='1' minSize='-1' maxSize='-1' dataType='2' elemType='5' repHandlerStruct='' visible='true' inheritsFrom='' autoAddNew='true' V281='3' V1='4' name='09' description='X.121 (CCITT)' incarnation='1'>
      <structNode t='150' idref='1'/>
    </child>
    <child t='167' id='10' V167='16' occurMaxTimes='1' minSize='-1' maxSize='-1' dataType='2' elemType='5' repHandlerStruct='' visible='true' inheritsFrom='' autoAddNew='true' V281='3' V1='4' name='10' description='Department of Defense (DoD) Activity Address Code' incarnation='1'>
      <structNode t='150' idref='1'/>
    </child>
    <child t='167' id='11' V167='16' occurMaxTimes='1' minSize='-1' maxSize='-1' dataType='2' elemType='5' repHandlerStruct='' visible='true' inheritsFrom='' autoAddNew='true' V281='3' V1='4' name='11' description='DEA (Drug Enforcement Administration)' incarnation='1'>
      <structNode t='150' idref='1'/>
    </child>
    <child t='167' id='12' V167='16' occurMaxTimes='1' minSize='-1' maxSize='-1' dataType='2' elemType='5' repHandlerStruct='' visible='true' inheritsFrom='' autoAddNew='true' V281='3' V1='4' name='12' description='Phone (Telephone Companies)' incarnation='1'>
      <structNode t='150' idref='1'/>
    </child>
    <child t='167' id='13' V167='16' occurMaxTimes='1' minSize='-1' maxSize='-1' dataType='2' elemType='5' repHandlerStruct='' visible='true' inheritsFrom='' autoAddNew='true' V281='3' V1='4' name='13' description='UCS Code (The UCS Code is a Code Used for UCS Transmissions; it includes the Area Code and Telephone Number of a Modem; it Does Not Include Punctuation, Blanks or Access Code)' incarnation='1'>
      <structNode t='150' idref='1'/>
    </child>
    <child t='167' id='14' V167='16' occurMaxTimes='1' minSize='-1' maxSize='-1' dataType='2' elemType='5' repHandlerStruct='' visible='true' inheritsFrom='' autoAddNew='true' V281='3' V1='4' name='14' description='Duns Plus Suffix' incarnation='1'>
      <structNode t='150' idref='1'/>
    </child>
    <child t='167' id='15' V167='16' occurMaxTimes='1' minSize='-1' maxSize='-1' dataType='2' elemType='5' repHandlerStruct='' visible='true' inheritsFrom='' autoAddNew='true' V281='3' V1='4' name='15' description='Petroleum Accountants Society of Canada Company Code' incarnation='1'>
      <structNode t='150' idref='1'/>
    </child>
    <child t='167' id='16' V167='16' occurMaxTimes='1' minSize='-1' maxSize='-1' dataType='2' elemType='5' repHandlerStruct='' visible='true' inheritsFrom='' autoAddNew='true' V281='3' V1='4' name='16' description='Duns Number With 4-Character Suffix' incarnation='1'>
      <structNode t='150' idref='1'/>
    </child>
    <child t='167' id='17' V167='16' occurMaxTimes='1' minSize='-1' maxSize='-1' dataType='2' elemType='5' repHandlerStruct='' visible='true' inheritsFrom='' autoAddNew='true' V281='3' V1='4' name='17' description='American Bankers Association (ABA) Transit Routing Number (Including Check Digit, 9 Digit)' incarnation='1'>
      <structNode t='150' idref='1'/>
    </child>
    <child t='167' id='18' V167='16' occurMaxTimes='1' minSize='-1' maxSize='-1' dataType='2' elemType='5' repHandlerStruct='' visible='true' inheritsFrom='' autoAddNew='true' V281='3' V1='4' name='18' description='Association of American Railroads (AAR) Standard Distribution Code' incarnation='1'>
      <structNode t='150' idref='1'/>
    </child>
    <child t='167' id='19' V167='16' occurMaxTimes='1' minSize='-1' maxSize='-1' dataType='2' elemType='5' repHandlerStruct='' visible='true' inheritsFrom='' autoAddNew='true' V281='3' V1='4' name='19' description='EDI Council of Australia (EDICA) Communications ID Number (COMM ID)' incarnation='1'>
      <structNode t='150' idref='1'/>
    </child>
    <child t='167' id='20' V167='16' occurMaxTimes='1' minSize='-1' maxSize='-1' dataType='2' elemType='5' repHandlerStruct='' visible='true' inheritsFrom='' autoAddNew='true' V281='3' V1='4' name='20' description='Health Industry Number (HIN)' incarnation='1'>
      <structNode t='150' idref='1'/>
    </child>
    <child t='167' id='21' V167='16' occurMaxTimes='1' minSize='-1' maxSize='-1' dataType='2' elemType='5' repHandlerStruct='' visible='true' inheritsFrom='' autoAddNew='true' V281='3' V1='4' name='21' description='Integrated Postsecondary Education Data System, or (IPEDS)' incarnation='1'>
      <structNode t='150' idref='1'/>
    </child>
    <child t='167' id='22' V167='16' occurMaxTimes='1' minSize='-1' maxSize='-1' dataType='2' elemType='5' repHandlerStruct='' visible='true' inheritsFrom='' autoAddNew='true' V281='3' V1='4' name='22' description='Federal Interagency Commission on Education, or FICE' incarnation='1'>
      <structNode t='150' idref='1'/>
    </child>
    <child t='167' id='23' V167='16' occurMaxTimes='1' minSize='-1' maxSize='-1' dataType='2' elemType='5' repHandlerStruct='' visible='true' inheritsFrom='' autoAddNew='true' V281='3' V1='4' name='23' description='National Center for Education Statistics Common Core of Data 12-Digit Number for Pre-K-Grade 12 Institutes, or NCES' incarnation='1'>
      <structNode t='150' idref='1'/>
    </child>
    <child t='167' id='24' V167='16' occurMaxTimes='1' minSize='-1' maxSize='-1' dataType='2' elemType='5' repHandlerStruct='' visible='true' inheritsFrom='' autoAddNew='true' V281='3' V1='4' name='24' description='The College Board&apos;s Admission Testing Program 4-Digit Code of Postsecondary Institutes, or ATP' incarnation='1'>
      <structNode t='150' idref='1'/>
    </child>
    <child t='167' id='25' V167='16' occurMaxTimes='1' minSize='-1' maxSize='-1' dataType='2' elemType='5' repHandlerStruct='' visible='true' inheritsFrom='' autoAddNew='true' V281='3' V1='4' name='25' description='ACT, Inc. 4-Digit Code of Postsecondary Institutions.' incarnation='1'>
      <structNode t='150' idref='1'/>
    </child>
    <child t='167' id='26' V167='16' occurMaxTimes='1' minSize='-1' maxSize='-1' dataType='2' elemType='5' repHandlerStruct='' visible='true' inheritsFrom='' autoAddNew='true' V281='3' V1='4' name='26' description='Statistics of Canada List of Postsecondary Institutions' incarnation='1'>
      <structNode t='150' idref='1'/>
    </child>
    <child t='167' id='27' V167='16' occurMaxTimes='1' minSize='-1' maxSize='-1' dataType='2' elemType='5' repHandlerStruct='' visible='true' inheritsFrom='' autoAddNew='true' V281='3' V1='4' name='27' description='Carrier Identification Number as assigned by Health Care Financing Administration (HCFA)' incarnation='1'>
      <structNode t='150' idref='1'/>
    </child>
    <child t='167' id='28' V167='16' occurMaxTimes='1' minSize='-1' maxSize='-1' dataType='2' elemType='5' repHandlerStruct='' visible='true' inheritsFrom='' autoAddNew='true' V281='3' V1='4' name='28' description='Fiscal Intermediary Identification Number as assigned by Health Care Financing Administration (HCFA)' incarnation='1'>
      <structNode t='150' idref='1'/>
    </child>
    <child t='167' id='29' V167='16' occurMaxTimes='1' minSize='-1' maxSize='-1' dataType='2' elemType='5' repHandlerStruct='' visible='true' inheritsFrom='' autoAddNew='true' V281='3' V1='4' name='29' description='Medicare Provider and Supplier Identification Number as assigned by Health Care Financing Administration (HCFA)' incarnation='1'>
      <structNode t='150' idref='1'/>
    </child>
    <child t='167' id='30' V167='16' occurMaxTimes='1' minSize='-1' maxSize='-1' dataType='2' elemType='5' repHandlerStruct='' visible='true' inheritsFrom='' autoAddNew='true' V281='3' V1='4' name='30' description='U.S. Federal Tax Identification Number' incarnation='1'>
      <structNode t='150' idref='1'/>
    </child>
    <child t='167' id='31' V167='16' occurMaxTimes='1' minSize='-1' maxSize='-1' dataType='2' elemType='5' repHandlerStruct='' visible='true' inheritsFrom='' autoAddNew='true' V281='3' V1='4' name='31' description='Jurisdiction Identification Number Plus 4 as assigned by the International Association of Industrial Accident Boards and Commissions (IAIABC)' incarnation='1'>
      <structNode t='150' idref='1'/>
    </child>
    <child t='167' id='32' V167='16' occurMaxTimes='1' minSize='-1' maxSize='-1' dataType='2' elemType='5' repHandlerStruct='' visible='true' inheritsFrom='' autoAddNew='true' V281='3' V1='4' name='32' description='U.S. Federal Employer Identification Number (FEIN)' incarnation='1'>
      <structNode t='150' idref='1'/>
    </child>
    <child t='167' id='33' V167='16' occurMaxTimes='1' minSize='-1' maxSize='-1' dataType='2' elemType='5' repHandlerStruct='' visible='true' inheritsFrom='' autoAddNew='true' V281='3' V1='4' name='33' description='National Association of Insurance Commissioners Company Code (NAIC)' incarnation='1'>
      <structNode t='150' idref='1'/>
    </child>
    <child t='167' id='34' V167='16' occurMaxTimes='1' minSize='-1' maxSize='-1' dataType='2' elemType='5' repHandlerStruct='' visible='true' inheritsFrom='' autoAddNew='true' V281='3' V1='4' name='34' description='Medicaid Provider and Supplier Identification Number as assigned by individual State Medicaid Agencies in conjunction with Health Care Financing Administration (HCFA)' incarnation='1'>
      <structNode t='150' idref='1'/>
    </child>
    <child t='167' id='35' V167='16' occurMaxTimes='1' minSize='-1' maxSize='-1' dataType='2' elemType='5' repHandlerStruct='' visible='true' inheritsFrom='' autoAddNew='true' V281='3' V1='4' name='35' description='Statistics Canada Canadian College Student Information System Institution Codes' incarnation='1'>
      <structNode t='150' idref='1'/>
    </child>
    <child t='167' id='36' V167='16' occurMaxTimes='1' minSize='-1' maxSize='-1' dataType='2' elemType='5' repHandlerStruct='' visible='true' inheritsFrom='' autoAddNew='true' V281='3' V1='4' name='36' description='Statistics Canada University Student Information System Institution Codes' incarnation='1'>
      <structNode t='150' idref='1'/>
    </child>
    <child t='167' id='37' V167='16' occurMaxTimes='1' minSize='-1' maxSize='-1' dataType='2' elemType='5' repHandlerStruct='' visible='true' inheritsFrom='' autoAddNew='true' V281='3' V1='4' name='37' description='Society of Property Information Compilers and Analysts' incarnation='1'>
      <structNode t='150' idref='1'/>
    </child>
    <child t='167' id='38' V167='16' occurMaxTimes='1' minSize='-1' maxSize='-1' dataType='2' elemType='5' repHandlerStruct='' visible='true' inheritsFrom='' autoAddNew='true' V281='3' V1='4' name='38' description='The College Board and ACT, Inc. 6-Digit Code List of Secondary Institutions' incarnation='1'>
      <structNode t='150' idref='1'/>
    </child>
    <child t='167' id='39' V167='16' occurMaxTimes='1' minSize='-1' maxSize='-1' dataType='2' elemType='5' repHandlerStruct='' visible='true' inheritsFrom='' autoAddNew='true' V281='3' V1='4' name='AM' description='Association Mexicana del Codigo de Producto (AMECOP) Communication ID' incarnation='1'>
      <structNode t='150' idref='1'/>
    </child>
    <child t='167' id='40' V167='16' occurMaxTimes='1' minSize='-1' maxSize='-1' dataType='2' elemType='5' repHandlerStruct='' visible='true' inheritsFrom='' autoAddNew='true' V281='3' V1='4' name='NR' description='National Retail Merchants Association (NRMA) - Assigned' incarnation='1'>
      <structNode t='150' idref='1'/>
    </child>
    <child t='167' id='41' V167='16' occurMaxTimes='1' minSize='-1' maxSize='-1' dataType='2' elemType='5' repHandlerStruct='' visible='true' inheritsFrom='' autoAddNew='true' V281='3' V1='4' name='SA' description='User Identification Number as assigned by the Safety and the Fitness Electronic Records (SAFER) System' incarnation='1'>
      <structNode t='150' idref='1'/>
    </child>
    <child t='167' id='42' V167='16' occurMaxTimes='1' minSize='-1' maxSize='-1' dataType='2' elemType='5' repHandlerStruct='' visible='true' inheritsFrom='' autoAddNew='true' V281='3' V1='4' name='SN' description='Standard Address Number' incarnation='1'>
      <structNode t='150' idref='1'/>
    </child>
    <child t='167' id='43' V167='16' occurMaxTimes='1' minSize='-1' maxSize='-1' dataType='2' elemType='5' repHandlerStruct='' visible='true' inheritsFrom='' autoAddNew='true' V281='3' V1='4' name='ZZ' description='Mutually Defined' incarnation='1'>
      <structNode t='150' idref='1'/>
    </child>
  </rootElem>
  <child t='162' id='44' V1='4' name='Representations' incarnation='1'>
  </child>
  <child t='165' id='45' V1='4' name='Document Bindings' incarnation='1'>
  </child>
</root>
