<?xml version="1.0" encoding="ISO-8859-15"?>

<rootTag>
  <school>
    <school_id>school_1</school_id>
    <students>
      <student>
        <id>1</id>
        <name>wang</name>
      </student>
      <student>
        <id>2</id>
        <name>zhang</name>
      </student>
      <student>
        <id>1</id>
        <name>wang</name>
      </student>
      <student>
        <id>2</id>
        <name>zhang</name>
      </student>
    </students>
  </school>
  <school>
    <school_id>school_2</school_id>
    <students>
      <student>
        <id>1</id>
        <name>li</name>
      </student>
      <student>
        <id>1</id>
        <name>li</name>
      </student>
    </students>
  </school>
</rootTag>
